{"name":"\n        [Lilith-Raws] 機動戰士鋼彈 水星的魔女 / Mobile Suit Gundam：The Witch from Mercury - 05 [Baha][WEB-DL][1080p][AVC AAC][CHT][MP4]","workName":"","source":"Blu-ray","resolution":"1080p","subtitleProvider":"","url":"http://www.kisssub.org/show-a0d84a9c1b664280213d7263f12d55c8f65adc27.html","isNew":false,"publishTime":"2022-10-30T17:16:39.000Z","isComplete":false,"generalRanking":5,"magnetLink":"magnet:?xt=urn:btih:a0d84a9c1b664280213d7263f12d55c8f65adc27&tr=http://open.acgtracker.com:1096/announce"}