{"name":"\n        [Lilith-Raws] 機動戰士鋼彈 水星的魔女 / Mobile Suit Gundam：The Witch from Mercury S02 - 10 [Baha][WEB-DL][1080p][AVC AAC][CHT][MP4]","workName":"","source":"Blu-ray","resolution":"1080p","subtitleProvider":"","url":"http://www.kisssub.org/show-ffe44ebbf47de7ff35ff091a6b367f6c0005e021.html","isNew":true,"publishTime":"2023-06-18T17:15:03.000Z","isComplete":false,"generalRanking":5,"magnetLink":"magnet:?xt=urn:btih:ffe44ebbf47de7ff35ff091a6b367f6c0005e021&tr=http://open.acgtracker.com:1096/announce"}